dache/__init__.py
dache/backends/__init__.py
dache/backends/base.py
dache/backends/filebased.py
dache/backends/leveldb.py
dache/backends/locmem.py
dache/backends/memcached.py
dache/backends/redis.py
dache/utils/__init__.py
dache/utils/encoding.py
dache/utils/files.py
dache/utils/functional.py
dache/utils/locks.py
dache/utils/module_loading.py
dache/utils/synch.py
dache-0.0.4.dist-info/DESCRIPTION.rst
dache-0.0.4.dist-info/METADATA
dache-0.0.4.dist-info/metadata.json
dache-0.0.4.dist-info/RECORD
dache-0.0.4.dist-info/top_level.txt
dache-0.0.4.dist-info/WHEEL
